vhub/__init__.py
vhub/cli.py
vhub-0.1.0.dist-info/METADATA
vhub-0.1.0.dist-info/WHEEL
vhub-0.1.0.dist-info/entry_points.txt
vhub-0.1.0.dist-info/top_level.txt
vhub-0.1.0.dist-info/RECORD
